{
  "$schema": "https://developer.microsoft.com/json-schemas/spfx-build/package-solution.schema.json",
  "solution": {
    "name": "sample-web-part-client-side-solution",
    "id": "44ec59f3-e5d1-4a50-9586-799f1040c7e7",
    "version": "1.0.0.0",
    "includeClientSideAssets": true,
    "isDomainIsolated": false,
    "developer": {
      "name": "",
      "websiteUrl": "",
      "privacyUrl": "",
      "termsOfUseUrl": "",
      "mpnId": ""
    }
  },
  "paths": {
    "zippedPackage": "solution/sample-web-part.sppkg"
  }
}
